celao/__init__.py
celao/main.py
celao/lib/__init__.py
celao/lib/correlation_methods.py
celao/lib/draw.py
celao/lib/preprocessing.py
celao/lib/utils.py
celao-0.3.2.dist-info/METADATA
celao-0.3.2.dist-info/WHEEL
celao-0.3.2.dist-info/top_level.txt
celao-0.3.2.dist-info/RECORD
