Metadata-Version: 2.4
Name: celao
Version: 0.3.2
Summary: Visualization tool for correlation n-ptychs of linguistic attributes
Home-page: https://github.com/Good03/celao/
Author: Good
Requires-Python: >=3.12
Requires-Dist: numpy
Requires-Dist: pandas
Requires-Dist: scikit-learn
Requires-Dist: matplotlib
Requires-Dist: seaborn
Requires-Dist: networkx
Requires-Dist: gensim
Dynamic: home-page
